{"keyArray":["pad7","vfaders","pad3","right1","pad15","left3","record","pad13","left1","pad8","play","down2","pad4","pad11","pad13on","push3","stop","push1","pad5","pad9","longfader","pad1","up1","left4","pad16","push1_2","pad14","pad1_2","left2","rotary2","up2","pad12","pad6","down1","hfaders","right4","pad2","pad10","pad14on","rotary1","right3","fader1","push4","right2","push2"],"uiBuilder":{"pad7":{"grdFrm":"{{34, 15}, {6, 6}}","mbg":{"title":false,"mutex":false,"btns":[{"rcvrs":[{"echNm2":"QUNEO-QUNEO","wantsEnbl":true,"echo":true,"src":"/MIDI/ch. 2/note [56]","tog":false}],"val":false},{"rcvrs":[{"echNm2":"QUNEO-QUNEO","wantsEnbl":true,"echo":true,"src":"/MIDI/ch. 2/note [58]","tog":false}],"val":false},{"rcvrs":[{"echNm2":"QUNEO-QUNEO","wantsEnbl":true,"echo":true,"src":"/MIDI/ch. 2/note [40]","tog":false}],"val":false},{"rcvrs":[{"echNm2":"QUNEO-QUNEO","wantsEnbl":true,"echo":true,"src":"/MIDI/ch. 2/note [42]","tog":false}],"val":false}],"toggle":true,"btnCount":"{2, 2}"},"sendEnabled":true,"pubType":2},"vfaders":{"min":0,"sendEnabled":true,"publishNorm":true,"msg":{"sldrs":[{"rcvrs":[{"src":"/Layers/Deck A/Opacity","wantsEnbl":true},{"echNm2":"QUNEO-QUNEO","wantsEnbl":true,"echo":true,"src":"/MIDI/ch. 0/ctrl [1]"}],"val":1},{"rcvrs":[{"echNm2":"QUNEO-QUNEO","wantsEnbl":true,"echo":true,"src":"/MIDI/ch. 0/ctrl [2]"}],"val":1},{"rcvrs":[{"src":"/Layers/Deck B/Opacity","wantsEnbl":true},{"echNm2":"QUNEO-QUNEO","wantsEnbl":true,"echo":true,"src":"/MIDI/ch. 0/ctrl [3]"}],"val":0},{"rcvrs":[{"echNm2":"QUNEO-QUNEO","wantsEnbl":true,"echo":true,"src":"/MIDI/ch. 0/ctrl [4]"}],"val":1}],"title":false,"sldrCount":"{4, 1}"},"fill":0,"max":1,"grdFrm":"{{4, 24}, {14, 9}}"},"pad3":{"grdFrm":"{{34, 21}, {6, 6}}","mbg":{"title":false,"mutex":false,"btns":[{"rcvrs":[{"echNm2":"QUNEO-QUNEO","wantsEnbl":true,"echo":true,"src":"/MIDI/ch. 2/note [24]","tog":false}],"val":false},{"rcvrs":[{"echNm2":"QUNEO-QUNEO","wantsEnbl":true,"echo":true,"src":"/MIDI/ch. 2/note [26]","tog":false}],"val":false},{"rcvrs":[{"echNm2":"QUNEO-QUNEO","wantsEnbl":true,"echo":true,"src":"/MIDI/ch. 2/note [8]","tog":false}],"val":false},{"rcvrs":[{"echNm2":"QUNEO-QUNEO","wantsEnbl":true,"echo":true,"src":"/MIDI/ch. 2/note [10]","tog":false}],"val":false}],"toggle":true,"btnCount":"{2, 2}"},"sendEnabled":true,"pubType":2},"right1":{"sendEnabled":true,"toggle":true,"val":false,"rcvrs":[{"echNm2":"QUNEO-QUNEO","wantsEnbl":true,"echo":true,"src":"/MIDI/ch. 0/note [37]","tog":false}],"mtxGrp":"Button Group","mtxFlg":false,"grdFrm":"{{3, 4}, {2, 2}}"},"pad15":{"minRange":0,"sendEnabled":true,"val":0,"rcvrs":[{"echNm2":"QUNEO-QUNEO","wantsEnbl":true,"echo":true,"src":"/MIDI/ch. 0/ctrl [17]"}],"publishNorm":true,"grdFrm":"{{34, 1}, {6, 6}}","maxRange":1},"left3":{"sendEnabled":true,"toggle":true,"val":false,"rcvrs":[{"echNm2":"QUNEO-QUNEO","wantsEnbl":true,"echo":true,"src":"/MIDI/ch. 0/note [40]","tog":false}],"mtxGrp":"Button Group","mtxFlg":false,"grdFrm":"{{1, 8}, {2, 2}}"},"record":{"sendEnabled":true,"toggle":true,"val":false,"rcvrs":[{"echNm2":"QUNEO-QUNEO","wantsEnbl":true,"echo":true,"src":"/MIDI/ch. 0/note [33]","tog":false}],"mtxGrp":"Button Group","mtxFlg":false,"grdFrm":"{{6, 0}, {2, 2}}"},"pad13":{"pubNorm":false,"sendEnabled":true,"X":{"rcvrs":[{"src":"/MIDI/ch. 0/ctrl [60]","echNm2":"QUNEO-QUNEO","wantsEnbl":true}],"val":0},"width":1,"height":1,"grdFrm":"{{20, 1}, {6, 6}}","Y":{"rcvrs":[{"src":"/MIDI/ch. 0/ctrl [61]","echNm2":"QUNEO-QUNEO","wantsEnbl":true}],"val":0}},"left1":{"sendEnabled":true,"toggle":true,"val":false,"rcvrs":[{"echNm2":"QUNEO-QUNEO","wantsEnbl":true,"echo":true,"src":"/MIDI/ch. 0/note [36]","tog":false}],"mtxGrp":"Button Group","mtxFlg":false,"grdFrm":"{{1, 4}, {2, 2}}"},"VVGridSize":"{47, 35}","pad8":{"grdFrm":"{{41, 15}, {6, 6}}","mbg":{"title":false,"mutex":false,"btns":[{"rcvrs":[{"echNm2":"QUNEO-QUNEO","wantsEnbl":true,"echo":true,"src":"/MIDI/ch. 2/note [60]","tog":false}],"val":false},{"rcvrs":[{"echNm2":"QUNEO-QUNEO","wantsEnbl":true,"echo":true,"src":"/MIDI/ch. 2/note [62]","tog":false}],"val":false},{"rcvrs":[{"echNm2":"QUNEO-QUNEO","wantsEnbl":true,"echo":true,"src":"/MIDI/ch. 2/note [44]","tog":false}],"val":false},{"rcvrs":[{"echNm2":"QUNEO-QUNEO","wantsEnbl":true,"echo":true,"src":"/MIDI/ch. 2/note [46]","tog":false}],"val":false}],"toggle":true,"btnCount":"{2, 2}"},"sendEnabled":true,"pubType":2},"play":{"sendEnabled":true,"toggle":true,"val":false,"rcvrs":[{"echNm2":"QUNEO-QUNEO","wantsEnbl":true,"echo":true,"src":"/MIDI/ch. 0/note [35]","tog":false}],"mtxGrp":"Button Group","mtxFlg":false,"grdFrm":"{{15, 0}, {2, 2}}"},"down2":{"sendEnabled":true,"toggle":true,"val":false,"rcvrs":[{"echNm2":"QUNEO-QUNEO","wantsEnbl":true,"echo":true,"src":"/MIDI/ch. 0/note [49]","tog":false}],"mtxGrp":"Button Group","mtxFlg":false,"grdFrm":"{{45, 31}, {2, 2}}"},"pad4":{"grdFrm":"{{41, 21}, {6, 6}}","mbg":{"title":false,"mutex":false,"btns":[{"rcvrs":[{"echNm2":"QUNEO-QUNEO","wantsEnbl":true,"echo":true,"src":"/MIDI/ch. 2/note [28]","tog":false}],"val":false},{"rcvrs":[{"echNm2":"QUNEO-QUNEO","wantsEnbl":true,"echo":true,"src":"/MIDI/ch. 2/note [30]","tog":false}],"val":false},{"rcvrs":[{"echNm2":"QUNEO-QUNEO","wantsEnbl":true,"echo":true,"src":"/MIDI/ch. 2/note [12]","tog":false}],"val":false},{"rcvrs":[{"echNm2":"QUNEO-QUNEO","wantsEnbl":true,"echo":true,"src":"/MIDI/ch. 2/note [14]","tog":false}],"val":false}],"toggle":true,"btnCount":"{2, 2}"},"sendEnabled":true,"pubType":2},"pad13on":{"sendEnabled":true,"toggle":true,"val":false,"rcvrs":[{"echNm2":"QUNEO-QUNEO","wantsEnbl":true,"src":"/MIDI/ch. 0/ctrl [59]","tog":false}],"mtxGrp":"Button Group","mtxFlg":false,"grdFrm":"{{22, 0}, {3, 1}}"},"pad11":{"minRange":0,"sendEnabled":true,"val":0,"rcvrs":[{"src":"/MIDI/ch. 0/ctrl [16]","echNm2":"QUNEO-QUNEO","wantsEnbl":true}],"publishNorm":true,"grdFrm":"{{34, 8}, {6, 6}}","maxRange":1},"VVGridMode":true,"push3":{"sendEnabled":true,"toggle":true,"val":true,"rcvrs":[{"src":"/Clock Surface/Beat 4","wantsEnbl":true}],"mtxFlg":true,"mtxGrp":"QuNeoClock Group","sndrs":[{"staticVelFlag":true,"staticVel":127,"enabled":true,"senderType":1,"noteRangeLow":0,"dataSenderType":1,"singleNoteThresh":5,"ctrl":0,"noteRangeMutexNoteoffs":false,"noteRangeSendNoteoffs":true,"noteRangeHigh":127,"singleNote":108,"outputLabel2":"QUNEO-QUNEO","channel":1}],"grdFrm":"{{44, 0}, {1, 1}}"},"stop":{"sendEnabled":true,"toggle":true,"val":false,"rcvrs":[{"echNm2":"QUNEO-QUNEO","wantsEnbl":true,"echo":true,"src":"/MIDI/ch. 0/note [34]","tog":false}],"mtxGrp":"Button Group","mtxFlg":false,"grdFrm":"{{10, 0}, {2, 2}}"},"pad9":{"minRange":0,"sendEnabled":true,"val":0,"rcvrs":[{"src":"/MIDI/ch. 0/ctrl [47]","echNm2":"QUNEO-QUNEO","wantsEnbl":true}],"publishNorm":true,"grdFrm":"{{20, 8}, {6, 6}}","maxRange":1},"push1_2":{"sendEnabled":true,"toggle":true,"val":false,"rcvrs":[{"src":"/Clock Surface/Beat 1","wantsEnbl":true}],"mtxFlg":true,"mtxGrp":"QuNeoClock Group","sndrs":[{"staticVelFlag":true,"staticVel":127,"enabled":true,"senderType":1,"noteRangeLow":0,"dataSenderType":1,"singleNoteThresh":5,"ctrl":0,"noteRangeMutexNoteoffs":false,"noteRangeSendNoteoffs":true,"noteRangeHigh":127,"singleNote":125,"outputLabel2":"QUNEO-QUNEO","channel":1}],"grdFrm":"{{41, 0}, {1, 1}}"},"pad5":{"grdFrm":"{{20, 15}, {6, 6}}","mbg":{"title":false,"mutex":false,"btns":[{"rcvrs":[{"echNm2":"QUNEO-QUNEO","wantsEnbl":true,"echo":true,"src":"/MIDI/ch. 2/note [48]","tog":false}],"val":false},{"rcvrs":[{"echNm2":"QUNEO-QUNEO","wantsEnbl":true,"echo":true,"src":"/MIDI/ch. 2/note [50]","tog":false}],"val":false},{"rcvrs":[{"echNm2":"QUNEO-QUNEO","wantsEnbl":true,"echo":true,"src":"/MIDI/ch. 2/note [32]","tog":false}],"val":false},{"rcvrs":[{"echNm2":"QUNEO-QUNEO","wantsEnbl":true,"echo":true,"src":"/MIDI/ch. 2/note [34]","tog":false}],"val":false}],"toggle":true,"btnCount":"{2, 2}"},"sendEnabled":true,"pubType":2},"push1":{"grdFrm":"{{-13, 29}, {6, 6}}","sendEnabled":true,"val":false,"toggle":true,"mtxGrp":"Button Group","mtxFlg":false},"longfader":{"sendEnabled":true,"minRange":0,"val":0,"rcvrs":[{"src":"/TCM 1/crossfader","wantsEnbl":true},{"echNm2":"QUNEO-QUNEO","wantsEnbl":true,"echo":true,"src":"/MIDI/ch. 0/ctrl [5]"}],"markArray":[{"mval":0.5}],"publishNorm":true,"grdFrm":"{{23, 29}, {21, 3}}","maxRange":1},"pad16":{"sendEnabled":true,"toggle":true,"val":false,"rcvrs":[{"echNm2":"QUNEO-QUNEO","wantsEnbl":true,"echo":true,"src":"/MIDI/ch. 0/note [31]","tog":false}],"mtxGrp":"Button Group","mtxFlg":false,"grdFrm":"{{41, 1}, {6, 6}}"},"up1":{"sendEnabled":true,"toggle":true,"val":false,"rcvrs":[{"echNm2":"QUNEO-QUNEO","wantsEnbl":true,"echo":true,"src":"/MIDI/ch. 0/note [46]","tog":false}],"mtxGrp":"Button Group","mtxFlg":false,"grdFrm":"{{20, 28}, {2, 2}}"},"pad1":{"grdFrm":"{{-27, 27}, {6, 6}}","mbg":{"title":false,"mutex":false,"btns":[{"val":false},{"val":false},{"val":false},{"val":false}],"toggle":true,"btnCount":"{2, 2}"},"sendEnabled":true,"pubType":2},"left4":{"sendEnabled":true,"toggle":true,"val":false,"rcvrs":[{"echNm2":"QUNEO-QUNEO","wantsEnbl":true,"echo":true,"src":"/MIDI/ch. 0/note [42]","tog":false}],"mtxGrp":"Button Group","mtxFlg":false,"grdFrm":"{{1, 10}, {2, 2}}"},"pad14":{"pubNorm":false,"sendEnabled":true,"X":{"rcvrs":[{"src":"/MIDI/ch. 0/ctrl [63]","echNm2":"QUNEO-QUNEO","wantsEnbl":true}],"val":0},"width":1,"height":1,"grdFrm":"{{27, 1}, {6, 6}}","Y":{"rcvrs":[{"src":"/MIDI/ch. 0/ctrl [64]","echNm2":"QUNEO-QUNEO","wantsEnbl":true}],"val":0}},"left2":{"sendEnabled":true,"toggle":true,"val":false,"rcvrs":[{"echNm2":"QUNEO-QUNEO","wantsEnbl":true,"echo":true,"src":"/MIDI/ch. 0/note [38]","tog":false}],"mtxGrp":"Button Group","mtxFlg":false,"grdFrm":"{{1, 6}, {2, 2}}"},"pad1_2":{"grdFrm":"{{20, 21}, {6, 6}}","mbg":{"title":false,"mutex":false,"btns":[{"rcvrs":[{"echNm2":"QUNEO-QUNEO","wantsEnbl":true,"echo":true,"src":"/MIDI/ch. 2/note [16]","tog":false}],"val":false},{"rcvrs":[{"echNm2":"QUNEO-QUNEO","wantsEnbl":true,"echo":true,"src":"/MIDI/ch. 2/note [18]","tog":false}],"val":false},{"rcvrs":[{"echNm2":"QUNEO-QUNEO","wantsEnbl":true,"echo":true,"src":"/MIDI/ch. 2/note [0]","tog":false}],"val":false},{"rcvrs":[{"echNm2":"QUNEO-QUNEO","wantsEnbl":true,"echo":true,"src":"/MIDI/ch. 2/note [2]","tog":false}],"val":false}],"toggle":true,"btnCount":"{2, 2}"},"sendEnabled":true,"pubType":2},"rotary2":{"minRange":0,"sendEnabled":true,"val":0.89763779527559051,"rcvrs":[{"echNm2":"QUNEO-QUNEO","wantsEnbl":true,"echo":true,"src":"/MIDI/ch. 0/ctrl [7]"}],"publishNorm":true,"grdFrm":"{{11, 13}, {8, 8}}","maxRange":1},"up2":{"sendEnabled":true,"toggle":true,"val":false,"rcvrs":[{"echNm2":"QUNEO-QUNEO","wantsEnbl":true,"echo":true,"src":"/MIDI/ch. 0/note [48]","tog":false}],"mtxGrp":"Button Group","mtxFlg":false,"grdFrm":"{{45, 28}, {2, 2}}"},"pad12":{"grdFrm":"{{41, 8}, {6, 6}}","mbg":{"title":false,"mutex":false,"btns":[{"rcvrs":[{"echNm2":"QUNEO-QUNEO","wantsEnbl":true,"echo":true,"src":"/MIDI/ch. 2/note [92]","tog":false}],"val":false},{"rcvrs":[{"echNm2":"QUNEO-QUNEO","wantsEnbl":true,"echo":true,"src":"/MIDI/ch. 2/note [94]","tog":false}],"val":false},{"rcvrs":[{"echNm2":"QUNEO-QUNEO","wantsEnbl":true,"echo":true,"src":"/MIDI/ch. 2/note [76]","tog":false}],"val":false},{"rcvrs":[{"echNm2":"QUNEO-QUNEO","wantsEnbl":true,"echo":true,"src":"/MIDI/ch. 2/note [78]","tog":false}],"val":false}],"toggle":true,"btnCount":"{2, 2}"},"sendEnabled":true,"pubType":2},"pad6":{"grdFrm":"{{27, 15}, {6, 6}}","mbg":{"title":false,"mutex":false,"btns":[{"rcvrs":[{"echNm2":"QUNEO-QUNEO","wantsEnbl":true,"echo":true,"src":"/MIDI/ch. 2/note [52]","tog":false}],"val":false},{"rcvrs":[{"echNm2":"QUNEO-QUNEO","wantsEnbl":true,"echo":true,"src":"/MIDI/ch. 2/note [54]","tog":false}],"val":false},{"rcvrs":[{"echNm2":"QUNEO-QUNEO","wantsEnbl":true,"echo":true,"src":"/MIDI/ch. 2/note [36]","tog":false}],"val":false},{"rcvrs":[{"echNm2":"QUNEO-QUNEO","wantsEnbl":true,"echo":true,"src":"/MIDI/ch. 2/note [38]","tog":false}],"val":false}],"toggle":true,"btnCount":"{2, 2}"},"sendEnabled":true,"pubType":2},"down1":{"sendEnabled":true,"toggle":true,"val":false,"rcvrs":[{"echNm2":"QUNEO-QUNEO","wantsEnbl":true,"echo":true,"src":"/MIDI/ch. 0/note [47]","tog":false}],"mtxGrp":"Button Group","mtxFlg":false,"grdFrm":"{{20, 31}, {2, 2}}"},"hfaders":{"min":0,"sendEnabled":true,"publishNorm":true,"msg":{"sldrs":[{"rcvrs":[{"echNm2":"QUNEO-QUNEO","wantsEnbl":true,"echo":true,"src":"/MIDI/ch. 0/ctrl [11]"}],"val":0},{"rcvrs":[{"echNm2":"QUNEO-QUNEO","wantsEnbl":true,"echo":true,"src":"/MIDI/ch. 0/ctrl [10]"}],"val":0},{"rcvrs":[{"echNm2":"QUNEO-QUNEO","wantsEnbl":true,"echo":true,"src":"/MIDI/ch. 0/ctrl [9]"}],"val":0},{"rcvrs":[{"echNm2":"QUNEO-QUNEO","wantsEnbl":true,"echo":true,"src":"/MIDI/ch. 0/ctrl [8]"}],"val":0}],"title":false,"sldrCount":"{1, 4}"},"fill":0,"max":1,"grdFrm":"{{5, 3}, {12, 9}}"},"right4":{"sendEnabled":true,"toggle":true,"val":false,"rcvrs":[{"echNm2":"QUNEO-QUNEO","wantsEnbl":true,"echo":true,"src":"/MIDI/ch. 0/note [43]","tog":false}],"mtxGrp":"Button Group","mtxFlg":false,"grdFrm":"{{3, 10}, {2, 2}}"},"pad2":{"grdFrm":"{{27, 21}, {6, 6}}","mbg":{"title":false,"mutex":false,"btns":[{"rcvrs":[{"echNm2":"QUNEO-QUNEO","wantsEnbl":true,"echo":true,"src":"/MIDI/ch. 2/note [20]","tog":false}],"val":false},{"rcvrs":[{"echNm2":"QUNEO-QUNEO","wantsEnbl":true,"echo":true,"src":"/MIDI/ch. 2/note [22]","tog":false}],"val":false},{"rcvrs":[{"echNm2":"QUNEO-QUNEO","wantsEnbl":true,"echo":true,"src":"/MIDI/ch. 2/note [4]","tog":false}],"val":false},{"rcvrs":[{"echNm2":"QUNEO-QUNEO","wantsEnbl":true,"echo":true,"src":"/MIDI/ch. 2/note [6]","tog":false}],"val":false}],"toggle":true,"btnCount":"{2, 2}"},"sendEnabled":true,"pubType":2},"pad10":{"minRange":0,"sendEnabled":true,"val":0,"rcvrs":[{"src":"/MIDI/ch. 0/ctrl [50]","echNm2":"QUNEO-QUNEO","wantsEnbl":true}],"publishNorm":true,"grdFrm":"{{27, 8}, {6, 6}}","maxRange":1},"pad14on":{"sendEnabled":true,"toggle":true,"val":false,"rcvrs":[{"echNm2":"QUNEO-QUNEO","wantsEnbl":true,"src":"/MIDI/ch. 0/ctrl [62]","tog":false}],"mtxGrp":"Button Group","mtxFlg":false,"grdFrm":"{{29, 0}, {3, 1}}"},"rotary1":{"minRange":0,"sendEnabled":true,"val":0.28346456692913385,"rcvrs":[{"echNm2":"QUNEO-QUNEO","wantsEnbl":true,"echo":true,"src":"/MIDI/ch. 0/ctrl [6]"}],"publishNorm":true,"grdFrm":"{{2, 13}, {8, 8}}","maxRange":1},"right3":{"sendEnabled":true,"toggle":true,"val":false,"rcvrs":[{"echNm2":"QUNEO-QUNEO","wantsEnbl":true,"echo":true,"src":"/MIDI/ch. 0/note [41]","tog":false}],"mtxGrp":"Button Group","mtxFlg":false,"grdFrm":"{{3, 8}, {2, 2}}"},"fader1":{"sendEnabled":true,"minRange":0,"val":0,"rcvrs":[{"src":"/MIDI/ch. 0/ctrl [79]","echNm2":"QUNEO-QUNEO","wantsEnbl":true}],"publishNorm":true,"sndrs":[{"staticVelFlag":true,"staticVel":127,"enabled":false,"senderType":1,"noteRangeLow":0,"dataSenderType":1,"singleNoteThresh":5,"ctrl":0,"noteRangeMutexNoteoffs":false,"noteRangeSendNoteoffs":true,"noteRangeHigh":127,"singleNote":44,"outputLabel2":"QUNEO-QUNEO","channel":0}],"maxRange":1,"grdFrm":"{{9, 21}, {3, 3}}"},"push4":{"sendEnabled":true,"toggle":true,"val":false,"rcvrs":[{"src":"/Clock 1/Beats/Beat03","wantsEnbl":true}],"mtxFlg":true,"mtxGrp":"QuNeoClock Group","sndrs":[{"staticVelFlag":true,"staticVel":127,"enabled":true,"senderType":1,"noteRangeLow":0,"dataSenderType":1,"singleNoteThresh":5,"ctrl":0,"noteRangeMutexNoteoffs":false,"noteRangeSendNoteoffs":true,"noteRangeHigh":127,"singleNote":126,"outputLabel2":"QUNEO-QUNEO","channel":1}],"grdFrm":"{{42, 0}, {1, 1}}"},"right2":{"sendEnabled":true,"toggle":true,"val":false,"rcvrs":[{"echNm2":"QUNEO-QUNEO","wantsEnbl":true,"echo":true,"src":"/MIDI/ch. 0/note [39]","tog":false}],"mtxGrp":"Button Group","mtxFlg":false,"grdFrm":"{{3, 6}, {2, 2}}"},"push2":{"sendEnabled":true,"toggle":true,"val":false,"rcvrs":[{"src":"/Clock Surface/Beat 3","wantsEnbl":true}],"mtxFlg":true,"mtxGrp":"QuNeoClock Group","sndrs":[{"staticVelFlag":true,"staticVel":127,"enabled":true,"senderType":1,"noteRangeLow":0,"dataSenderType":1,"singleNoteThresh":5,"ctrl":0,"noteRangeMutexNoteoffs":false,"noteRangeSendNoteoffs":true,"noteRangeHigh":127,"singleNote":110,"outputLabel2":"QUNEO-QUNEO","channel":1}],"grdFrm":"{{43, 0}, {1, 1}}"}},"classArray":["MultiButtonElement","MultiSliderElement","MultiButtonElement","Button","Slider","Button","Button","PositionElement","Button","MultiButtonElement","Button","Button","MultiButtonElement","Slider","Button","Button","Button","Button","MultiButtonElement","Slider","Slider","MultiButtonElement","Button","Button","Button","Button","PositionElement","MultiButtonElement","Button","Slider","Button","MultiButtonElement","MultiButtonElement","Button","MultiSliderElement","Button","MultiButtonElement","Slider","Button","Slider","Button","Slider","Button","Button","Button"]}